damgard_jurik/__init__.py
damgard_jurik/crypto.py
damgard_jurik/prime_gen.py
damgard_jurik/shamir.py
damgard_jurik/utils.py
damgard_jurik-0.0.3.dist-info/LICENSE
damgard_jurik-0.0.3.dist-info/METADATA
damgard_jurik-0.0.3.dist-info/WHEEL
damgard_jurik-0.0.3.dist-info/top_level.txt
damgard_jurik-0.0.3.dist-info/RECORD
