Metadata-Version: 2.1
Name: damgard-jurik
Version: 0.0.3
Summary: Homomorphic encryption using the threshold variant of the Damgard-Jurik cryptosystem.
Home-page: https://github.com/cryptovoting/damgard-jurik
Author: Nicholas Boucher, Luka Govedič, Pasapol Saowakon, Kyle Swanson
Author-email: swansonk.14@gmail.com
License: UNKNOWN
Platform: UNKNOWN
Classifier: Programming Language :: Python :: 3
Classifier: License :: OSI Approved :: MIT License
Classifier: Operating System :: OS Independent
Requires-Dist: gmpy2
